hades/__init__.py
hades/core/__init__.py
hades/core/event.py
hades/core/hades.py
hades/core/process.py
hades/logging.py
hades/py.typed
hades/time/__init__.py
hades/time/day_steps.py
hades/time/event.py
hades/time/logging.py
hades/time/process.py
hades/visualisation/__init__.py
hades/visualisation/networkx.py
hades/visualisation/websockets.py
hades_framework-2.0.0.dist-info/LICENSE.md
hades_framework-2.0.0.dist-info/METADATA
hades_framework-2.0.0.dist-info/WHEEL
hades_framework-2.0.0.dist-info/RECORD
