Metadata-Version: 2.1
Name: hades-framework
Version: 2.0.0
Summary: Hades Asynchronous Discrete-Event Simulation
License: Apache-2.0
Author: Ki Insurance Team
Requires-Python: >=3.10,<4.0
Classifier: License :: OSI Approved :: Apache Software License
Classifier: Programming Language :: Python :: 3
Classifier: Programming Language :: Python :: 3.10
Classifier: Programming Language :: Python :: 3.11
Provides-Extra: visualisation
Requires-Dist: networkx (>=3.1,<4.0) ; extra == "visualisation"
Requires-Dist: networkx-stubs (>=0.0.1,<0.0.2) ; extra == "visualisation"
Requires-Dist: pydantic (>=2.8.2,<3.0.0)
Requires-Dist: websockets (>=11.0.3,<12.0.0) ; extra == "visualisation"
